statclean/__init__.py
statclean/cleaner.py
statclean/utils.py
statclean-0.1.3.dist-info/licenses/LICENSE
tests/__init__.py
tests/test_statclean.py
statclean-0.1.3.dist-info/METADATA
statclean-0.1.3.dist-info/WHEEL
statclean-0.1.3.dist-info/top_level.txt
statclean-0.1.3.dist-info/RECORD
