Metadata-Version: 2.4
Name: statclean
Version: 0.1.3
Summary: A comprehensive statistical data preprocessing and outlier detection library with formal statistical testing and publication-quality reporting
Home-page: https://github.com/SubaashNair/StatClean
Author: Subashanan Nair
Author-email: subaashnair12@gmail.com
Project-URL: Homepage, https://subaashnair.github.io/StatClean/
Project-URL: Documentation, https://subaashnair.github.io/StatClean/
Project-URL: Source, https://github.com/SubaashNair/StatClean
Project-URL: Tracker, https://github.com/SubaashNair/StatClean/issues
Project-URL: API Reference, https://subaashnair.github.io/StatClean/api-reference
Project-URL: Examples, https://subaashnair.github.io/StatClean/examples
Classifier: Development Status :: 4 - Beta
Classifier: Intended Audience :: Science/Research
Classifier: License :: OSI Approved :: MIT License
Classifier: Operating System :: OS Independent
Classifier: Programming Language :: Python :: 3
Classifier: Programming Language :: Python :: 3.7
Classifier: Programming Language :: Python :: 3.8
Classifier: Programming Language :: Python :: 3.9
Classifier: Programming Language :: Python :: 3.10
Classifier: Topic :: Scientific/Engineering :: Information Analysis
Classifier: Topic :: Scientific/Engineering :: Mathematics
Classifier: Topic :: Software Development :: Libraries :: Python Modules
Requires-Python: >=3.7
License-File: LICENSE
Requires-Dist: numpy>=1.19.0
Requires-Dist: pandas>=1.2.0
Requires-Dist: matplotlib>=3.3.0
Requires-Dist: seaborn>=0.11.0
Requires-Dist: scipy>=1.6.0
Requires-Dist: tqdm>=4.60.0
Dynamic: author
Dynamic: author-email
Dynamic: classifier
Dynamic: description
Dynamic: description-content-type
Dynamic: home-page
Dynamic: license-file
Dynamic: project-url
Dynamic: requires-dist
Dynamic: requires-python
Dynamic: summary
